drug_toxicity/__init__.py
drug_toxicity/chemicals.py
drug_toxicity/liver.py
drug_toxicity/py.typed
drug_toxicity/reactions.py
drug_toxicity/validator.py
drug_toxicity-0.3.1.dist-info/licenses/LICENSE
drug_toxicity-0.3.1.dist-info/METADATA
drug_toxicity-0.3.1.dist-info/WHEEL
drug_toxicity-0.3.1.dist-info/top_level.txt
drug_toxicity-0.3.1.dist-info/RECORD
